<?xml version="1.0" encoding="UTF-8"?><sv:node xmlns:sv="http://www.jcp.org/jcr/sv/1.0" sv:name="hst:configurations">
  <sv:property sv:name="jcr:primaryType" sv:type="Name">
    <sv:value>hst:configurations</sv:value>
  </sv:property>
  <sv:node sv:name="hst:default">
    <sv:property sv:name="jcr:primaryType" sv:type="Name">
      <sv:value>hst:configuration</sv:value>
    </sv:property>
    <sv:node sv:name="hst:sitemap">
      <sv:property sv:name="jcr:primaryType" sv:type="Name">
        <sv:value>hst:sitemap</sv:value>
      </sv:property>
    </sv:node>
    <sv:node sv:name="hst:pages">
      <sv:property sv:name="jcr:primaryType" sv:type="Name">
        <sv:value>hst:pages</sv:value>
      </sv:property>
    </sv:node>
    <sv:node sv:name="hst:components">
      <sv:property sv:name="jcr:primaryType" sv:type="Name">
        <sv:value>hst:components</sv:value>
      </sv:property>
    </sv:node>
    <sv:node sv:name="hst:templates">
      <sv:property sv:name="jcr:primaryType" sv:type="Name">
        <sv:value>hst:templates</sv:value>
      </sv:property>
    </sv:node>
    <sv:node sv:name="hst:sitemenus">
      <sv:property sv:name="jcr:primaryType" sv:type="Name">
        <sv:value>hst:sitemenus</sv:value>
      </sv:property>
    </sv:node>
    <sv:node sv:name="hst:sitemapitemhandlers">
      <sv:property sv:name="jcr:primaryType" sv:type="Name">
        <sv:value>hst:sitemapitemhandlers</sv:value>
      </sv:property>
    </sv:node>
    <sv:node sv:name="hst:catalog">
      <sv:property sv:name="jcr:primaryType" sv:type="Name">
        <sv:value>hst:catalog</sv:value>
      </sv:property>
    </sv:node>
  </sv:node>
  <sv:node sv:name="motricebpm-common">
    <sv:property sv:name="jcr:primaryType" sv:type="Name">
      <sv:value>hst:configuration</sv:value>
    </sv:property>
    <sv:node sv:name="hst:sitemap">
      <sv:property sv:name="jcr:primaryType" sv:type="Name">
        <sv:value>hst:sitemap</sv:value>
      </sv:property>
      <sv:node sv:name="inbox">
        <sv:property sv:name="jcr:primaryType" sv:type="Name">
          <sv:value>hst:sitemapitem</sv:value>
        </sv:property>
        <sv:property sv:name="hst:componentconfigurationid" sv:type="String">
          <sv:value>hst:pages/motriceinbox</sv:value>
        </sv:property>
      </sv:node>
    </sv:node>
    <sv:node sv:name="hst:abstractpages">
      <sv:property sv:name="jcr:primaryType" sv:type="Name">
        <sv:value>hst:pages</sv:value>
      </sv:property>
    </sv:node>
    <sv:node sv:name="hst:workspace">
      <sv:property sv:name="jcr:primaryType" sv:type="Name">
        <sv:value>hst:workspace</sv:value>
      </sv:property>
      <sv:node sv:name="hst:containers">
        <sv:property sv:name="jcr:primaryType" sv:type="Name">
          <sv:value>hst:containercomponentfolder</sv:value>
        </sv:property>
      </sv:node>
    </sv:node>
    <sv:node sv:name="hst:pages">
      <sv:property sv:name="jcr:primaryType" sv:type="Name">
        <sv:value>hst:pages</sv:value>
      </sv:property>
      <sv:node sv:name="motriceinbox">
        <sv:property sv:name="jcr:primaryType" sv:type="Name">
          <sv:value>hst:component</sv:value>
        </sv:property>
        <sv:property sv:name="hst:referencecomponent" sv:type="String">
          <sv:value>hst:components/motriceinbox</sv:value>
        </sv:property>
      </sv:node>
    </sv:node>
    <sv:node sv:name="hst:components">
      <sv:property sv:name="jcr:primaryType" sv:type="Name">
        <sv:value>hst:components</sv:value>
      </sv:property>
      <sv:node sv:name="motriceinbox">
        <sv:property sv:name="jcr:primaryType" sv:type="Name">
          <sv:value>hst:component</sv:value>
        </sv:property>
        <sv:property sv:name="hst:componentclassname" sv:type="String">
          <sv:value>org.motrice.bpm.hippo.components.Inbox</sv:value>
        </sv:property>
        <sv:property sv:name="hst:template" sv:type="String">
          <sv:value>motriceinbox.main.content</sv:value>
        </sv:property>
      </sv:node>
    </sv:node>
    <sv:node sv:name="hst:templates">
      <sv:property sv:name="jcr:primaryType" sv:type="Name">
        <sv:value>hst:templates</sv:value>
      </sv:property>
    </sv:node>
    <sv:node sv:name="hst:sitemenus">
      <sv:property sv:name="jcr:primaryType" sv:type="Name">
        <sv:value>hst:sitemenus</sv:value>
      </sv:property>
    </sv:node>
    <sv:node sv:name="hst:sitemapitemhandlers">
      <sv:property sv:name="jcr:primaryType" sv:type="Name">
        <sv:value>hst:sitemapitemhandlers</sv:value>
      </sv:property>
    </sv:node>
    <sv:node sv:name="hst:catalog">
      <sv:property sv:name="jcr:primaryType" sv:type="Name">
        <sv:value>hst:catalog</sv:value>
      </sv:property>
    </sv:node>
  </sv:node>
  <sv:node sv:name="motricebpm-common-web">
    <sv:property sv:name="jcr:primaryType" sv:type="Name">
      <sv:value>hst:configuration</sv:value>
    </sv:property>
    <sv:node sv:name="hst:templates">
      <sv:property sv:name="jcr:primaryType" sv:type="Name">
        <sv:value>hst:templates</sv:value>
      </sv:property>
      <sv:node sv:name="motriceinbox.main.content">
        <sv:property sv:name="jcr:primaryType" sv:type="Name">
          <sv:value>hst:template</sv:value>
        </sv:property>
        <sv:property sv:name="hst:renderpath" sv:type="String">
          <sv:value>jsp/motricebpm/common/web/motriceinbox/main/content.jsp</sv:value>
        </sv:property>
      </sv:node>
    </sv:node>
  </sv:node>
  <sv:node sv:name="common">
    <sv:property sv:name="jcr:primaryType" sv:type="Name">
      <sv:value>hst:configuration</sv:value>
    </sv:property>
    <sv:node sv:name="hst:sitemap">
      <sv:property sv:name="jcr:primaryType" sv:type="Name">
        <sv:value>hst:sitemap</sv:value>
      </sv:property>
    </sv:node>
    <sv:node sv:name="hst:abstractpages">
      <sv:property sv:name="jcr:primaryType" sv:type="Name">
        <sv:value>hst:pages</sv:value>
      </sv:property>
    </sv:node>
    <sv:node sv:name="hst:workspace">
      <sv:property sv:name="jcr:primaryType" sv:type="Name">
        <sv:value>hst:workspace</sv:value>
      </sv:property>
      <sv:node sv:name="hst:containers">
        <sv:property sv:name="jcr:primaryType" sv:type="Name">
          <sv:value>hst:containercomponentfolder</sv:value>
        </sv:property>
      </sv:node>
    </sv:node>
    <sv:node sv:name="hst:pages">
      <sv:property sv:name="jcr:primaryType" sv:type="Name">
        <sv:value>hst:pages</sv:value>
      </sv:property>
    </sv:node>
    <sv:node sv:name="hst:components">
      <sv:property sv:name="jcr:primaryType" sv:type="Name">
        <sv:value>hst:components</sv:value>
      </sv:property>
    </sv:node>
    <sv:node sv:name="hst:templates">
      <sv:property sv:name="jcr:primaryType" sv:type="Name">
        <sv:value>hst:templates</sv:value>
      </sv:property>
    </sv:node>
    <sv:node sv:name="hst:sitemenus">
      <sv:property sv:name="jcr:primaryType" sv:type="Name">
        <sv:value>hst:sitemenus</sv:value>
      </sv:property>
    </sv:node>
    <sv:node sv:name="hst:sitemapitemhandlers">
      <sv:property sv:name="jcr:primaryType" sv:type="Name">
        <sv:value>hst:sitemapitemhandlers</sv:value>
      </sv:property>
    </sv:node>
    <sv:node sv:name="hst:catalog">
      <sv:property sv:name="jcr:primaryType" sv:type="Name">
        <sv:value>hst:catalog</sv:value>
      </sv:property>
    </sv:node>
  </sv:node>
  <sv:node sv:name="demomotricehippoproject">
    <sv:property sv:name="jcr:primaryType" sv:type="Name">
      <sv:value>hst:configuration</sv:value>
    </sv:property>
    <sv:property sv:name="hst:inheritsfrom" sv:type="String" sv:multiple="true">
      <sv:value>../common</sv:value>
      <sv:value>../motricebpm-common</sv:value>
      <sv:value>../motricebpm-common-web</sv:value>
    </sv:property>
  </sv:node>
</sv:node>
